continuo/__init__.py
continuo/__main__.py
continuo/cli.py
continuo/config.py
continuo/duration.py
continuo/effects.py
continuo/enums.py
continuo/generator.py
continuo/layer.py
continuo/music_algorithm.py
continuo/output.py
continuo/playback.py
continuo/py.typed
continuo/scale.py
continuo/timeline.py
continuo-0.3.0.dist-info/LICENSE
continuo-0.3.0.dist-info/METADATA
continuo-0.3.0.dist-info/WHEEL
continuo-0.3.0.dist-info/top_level.txt
continuo-0.3.0.dist-info/RECORD
