Metadata-Version: 2.1
Name: continuo
Version: 0.3.0
Summary: Procedural music generator
Home-page: https://github.com/rbaltrusch/continuo
Author: Richard Baltrusch
License: AGPLv3
Keywords: python
Classifier: Development Status :: 4 - Beta
Classifier: Environment :: Console
Classifier: Intended Audience :: Developers
Classifier: Intended Audience :: End Users/Desktop
Classifier: License :: OSI Approved :: GNU Affero General Public License v3 or later (AGPLv3+)
Classifier: Programming Language :: Python
Classifier: Programming Language :: Python :: 3
Classifier: Programming Language :: Python :: 3 :: Only
Classifier: Programming Language :: Python :: 3.8
Classifier: Programming Language :: Python :: 3.9
Classifier: Programming Language :: Python :: 3.10
Classifier: Programming Language :: Python :: 3.11
Classifier: Topic :: Artistic Software
Classifier: Topic :: Desktop Environment
Classifier: Topic :: Multimedia
Classifier: Topic :: Multimedia :: Sound/Audio
Classifier: Topic :: Multimedia :: Sound/Audio :: Sound Synthesis
Classifier: Typing :: Typed
Requires-Python: >=3.8
License-File: LICENSE
Requires-Dist: musical ==0.3.0
Requires-Dist: numpy ==1.24.0
Requires-Dist: pygame ==2.5.2
